README.rst
setup.py
pytest_html_thread/__init__.py
pytest_html_thread/extras.py
pytest_html_thread/hooks.py
pytest_html_thread/plugin.py
pytest_html_thread.egg-info/PKG-INFO
pytest_html_thread.egg-info/SOURCES.txt
pytest_html_thread.egg-info/dependency_links.txt
pytest_html_thread.egg-info/entry_points.txt
pytest_html_thread.egg-info/requires.txt
pytest_html_thread.egg-info/top_level.txt
pytest_html_thread/resources/main.js
pytest_html_thread/resources/style.css